windows_adb_screen_capture/LICENSE
windows_adb_screen_capture/README.MD
windows_adb_screen_capture/__init__.py
windows_adb_screen_capture/requirements.txt
windows_adb_screen_capture/thirdparty.json
windows_adb_screen_capture-0.17.dist-info/LICENSE.rst
windows_adb_screen_capture-0.17.dist-info/METADATA
windows_adb_screen_capture-0.17.dist-info/WHEEL
windows_adb_screen_capture-0.17.dist-info/top_level.txt
windows_adb_screen_capture-0.17.dist-info/RECORD
